imf_data_fetcher/__init__.py
imf_data_fetcher/consts.py
imf_data_fetcher/main.py
imf_data_fetcher/queries.py
imf_data_fetcher/utils.py
imf_data_fetcher-0.1.dist-info/METADATA
imf_data_fetcher-0.1.dist-info/WHEEL
imf_data_fetcher-0.1.dist-info/top_level.txt
imf_data_fetcher-0.1.dist-info/RECORD
