Metadata-Version: 2.1
Name: imf-data-fetcher
Version: 0.1
Summary: Interacts with the International Monetary Fund API (SDMX 3.0) to retrieve macroeconomic data.
Home-page: https://github.com/nndjoli/imf-data-fetcher
Author: nndjoli
License: UNKNOWN
Platform: UNKNOWN
Requires-Dist: pandas
Requires-Dist: httpx
Requires-Dist: nest-asyncio
